insta_message_analyzer/__init__.py
insta_message_analyzer/analysis/__init__.py
insta_message_analyzer/analysis/analysis_types.py
insta_message_analyzer/analysis/pipeline.py
insta_message_analyzer/analysis/protocol.py
insta_message_analyzer/analysis/strategies/__init__.py
insta_message_analyzer/analysis/strategies/activity.py
insta_message_analyzer/analysis/strategies/network.py
insta_message_analyzer/analysis/validation.py
insta_message_analyzer/data/__init__.py
insta_message_analyzer/data/loader.py
insta_message_analyzer/data/preprocessor.py
insta_message_analyzer/main.py
insta_message_analyzer/utils/__init__.py
insta_message_analyzer/utils/setup_logging.py
insta_message_analyzer/visualization/__init__.py
insta_message_analyzer/visualization/plotter.py
insta_message_analyzer-0.1.0.dist-info/LICENSE
insta_message_analyzer-0.1.0.dist-info/METADATA
insta_message_analyzer-0.1.0.dist-info/WHEEL
insta_message_analyzer-0.1.0.dist-info/entry_points.txt
insta_message_analyzer-0.1.0.dist-info/RECORD
